click_type_test.py
click_type_test-2.0.2.dist-info/licenses/LICENSE.txt
click_type_test-2.0.2.dist-info/METADATA
click_type_test-2.0.2.dist-info/WHEEL
click_type_test-2.0.2.dist-info/top_level.txt
click_type_test-2.0.2.dist-info/RECORD
