Metadata-Version: 2.4
Name: click-type-test
Version: 2.0.2
Summary: Test that type annotations match click parameter types
Author-email: Stephen Rosen <sirosen@globus.org>
License: MIT
Project-URL: source, https://github.com/sirosen/click-type-test
Classifier: Development Status :: 5 - Production/Stable
Classifier: Programming Language :: Python
Classifier: Programming Language :: Python :: 3.10
Classifier: Programming Language :: Python :: 3.11
Classifier: Programming Language :: Python :: 3.12
Classifier: Programming Language :: Python :: 3.13
Classifier: Programming Language :: Python :: 3.14
Classifier: Programming Language :: Python :: Implementation :: CPython
Requires-Python: >=3.10
License-File: LICENSE.txt
Requires-Dist: click>=8.1.0
Dynamic: license-file
